metadata_curation_client/__init__.py
metadata_curation_client/curation_api_client.py
metadata_curation_client/source_manager.py
metadata_curation_client-0.9.2.dist-info/licenses/LICENSE
metadata_curation_client-0.9.2.dist-info/METADATA
metadata_curation_client-0.9.2.dist-info/WHEEL
metadata_curation_client-0.9.2.dist-info/top_level.txt
metadata_curation_client-0.9.2.dist-info/RECORD
