Metadata-Version: 2.4
Name: metadata-curation-client
Version: 0.9.2
Summary: API client for metadata curation platforms
Author: Digital Edition Curation Team
License: MIT
Project-URL: Homepage, https://github.com/yourusername/digital-edition-curation
Project-URL: Repository, https://github.com/yourusername/digital-edition-curation
Project-URL: Issues, https://github.com/yourusername/digital-edition-curation/issues
Classifier: Development Status :: 4 - Beta
Classifier: Intended Audience :: Developers
Classifier: License :: OSI Approved :: MIT License
Classifier: Programming Language :: Python :: 3
Classifier: Programming Language :: Python :: 3.8
Classifier: Programming Language :: Python :: 3.9
Classifier: Programming Language :: Python :: 3.10
Classifier: Programming Language :: Python :: 3.11
Classifier: Programming Language :: Python :: 3.12
Requires-Python: >=3.8
License-File: LICENSE
Requires-Dist: requests>=2.28.0
Provides-Extra: dev
Requires-Dist: pytest>=7.0; extra == "dev"
Requires-Dist: black; extra == "dev"
Requires-Dist: isort; extra == "dev"
Requires-Dist: mypy; extra == "dev"
Dynamic: license-file
